luster/__init__.py
luster/client.py
luster/enums.py
luster/events.py
luster/exceptions.py
luster/http.py
luster/websocket.py
luster/internal/__init__.py
luster/internal/events_handler.py
luster/internal/types.py
luster/types/__init__.py
luster/types/enums.py
luster/types/node_info.py
luster/types/websocket.py
luster-0.1.0a2.dist-info/LICENSE
luster-0.1.0a2.dist-info/METADATA
luster-0.1.0a2.dist-info/WHEEL
luster-0.1.0a2.dist-info/top_level.txt
luster-0.1.0a2.dist-info/RECORD
