Metadata-Version: 2.1
Name: luster
Version: 0.1.0a2
Summary: [Pre-Alpha] Python library for Revolt.chat.
Home-page: https://github.com/nerdguyahmad/luster
Author: nerdguyahmad
License: MIT
Project-URL: Documentation, https://luster.readthedocs.io
Project-URL: Issue tracker, https://github.com/nerdguyahmad/luster/issues
Classifier: Development Status :: 2 - Pre-Alpha
Classifier: License :: OSI Approved :: MIT License
Classifier: Intended Audience :: Developers
Classifier: Natural Language :: English
Classifier: Operating System :: OS Independent
Classifier: Programming Language :: Python :: 3.8
Classifier: Programming Language :: Python :: 3.9
Classifier: Programming Language :: Python :: 3.10
Classifier: Topic :: Internet
Classifier: Topic :: Software Development :: Libraries
Classifier: Topic :: Software Development :: Libraries :: Python Modules
Classifier: Topic :: Utilities
Classifier: Typing :: Typed
Requires-Python: >=3.8.0
License-File: LICENSE
Requires-Dist: aiohttp (==3.8.1)
Requires-Dist: typing-extensions (>=4.2.0)
